fibo/__init__.py
fibo/__main__.py
fibo/cli.py
fibo/fibo.py
tortillapatata_fibo-0.1.2.dist-info/METADATA
tortillapatata_fibo-0.1.2.dist-info/WHEEL
tortillapatata_fibo-0.1.2.dist-info/entry_points.txt
tortillapatata_fibo-0.1.2.dist-info/top_level.txt
tortillapatata_fibo-0.1.2.dist-info/RECORD
