Metadata-Version: 2.4
Name: tortillapatata-fibo
Version: 0.1.2
Summary: Simple Fibonacci generator
Author-email: Alper <alper.bingol97@gmail.com>
License: MIT
Keywords: fibonacci,cli,math
Classifier: Programming Language :: Python :: 3
Classifier: License :: OSI Approved :: MIT License
Classifier: Operating System :: OS Independent
Requires-Python: >=3.7
